fib.py
fibonacci24595645-0.1.dist-info/METADATA
fibonacci24595645-0.1.dist-info/WHEEL
fibonacci24595645-0.1.dist-info/entry_points.txt
fibonacci24595645-0.1.dist-info/top_level.txt
fibonacci24595645-0.1.dist-info/RECORD
